pdbwhereami.py
pdbwhereami-1.0.1.dist-info/LICENSE
pdbwhereami-1.0.1.dist-info/METADATA
pdbwhereami-1.0.1.dist-info/WHEEL
pdbwhereami-1.0.1.dist-info/top_level.txt
pdbwhereami-1.0.1.dist-info/RECORD
