Metadata-Version: 2.1
Name: pdbwhereami
Version: 1.0.1
Summary: By leveraging `pdbwhereami`, developers can create more robust, maintainable, and easier-to-debug code.
Home-page: https://github.com/bhagavansprasad/pdbwhereami.git
Author: Bhagavan
Author-email: bhagavansprasad@gmail.com
License: UNKNOWN
Platform: UNKNOWN
Classifier: Programming Language :: Python :: 3
Classifier: License :: OSI Approved :: MIT License
Classifier: Operating System :: OS Independent
Requires-Python: >=3.6
License-File: LICENSE
